README.md
setup.py
tangUtils/__init__.py
tangUtils/ftp.py
tangUtils/mail.py
tangUtils/main.py
tangUtils/utils.py
tangUtils.egg-info/PKG-INFO
tangUtils.egg-info/SOURCES.txt
tangUtils.egg-info/dependency_links.txt
tangUtils.egg-info/entry_points.txt
tangUtils.egg-info/requires.txt
tangUtils.egg-info/top_level.txt