Metadata-Version: 2.1
Name: tangUtils
Version: 0.2.0
Summary: 文件/目录相关utils
Home-page: https://github.com/xiaomingTang/python-utils
Author: xiaomingtang
Author-email: 1038761793@qq.com
License: UNKNOWN
Platform: UNKNOWN
